levv/PROJECT.txt
levv/__init__.py
levv/main.py
levv-0.1.7.data/scripts/levv
levv-0.1.7.dist-info/LICENSE
levv-0.1.7.dist-info/METADATA
levv-0.1.7.dist-info/WHEEL
levv-0.1.7.dist-info/top_level.txt
levv-0.1.7.dist-info/RECORD
