Metadata-Version: 2.1
Name: levv
Version: 0.1.7
Summary: Graphical log file viewer
Home-page: https://github.com/wheresjames/levv
Author: Robert Umbehant
Author-email: levv@wheresjames.com
License: MIT
Platform: UNKNOWN
Requires-Dist: argparse
Requires-Dist: psutil
Requires-Dist: python-dateutil
